CHANGELOG.rst
LICENSE.txt
README.rst
sklearn_instrumentation/__init__.py
sklearn_instrumentation/_version.py
sklearn_instrumentation/config.py
sklearn_instrumentation/instrumentor.py
sklearn_instrumentation/instruments/__init__.py
sklearn_instrumentation/instruments/base.py
sklearn_instrumentation/instruments/cprofile.py
sklearn_instrumentation/instruments/datadog.py
sklearn_instrumentation/instruments/logging.py
sklearn_instrumentation/instruments/memory_profiler.py
sklearn_instrumentation/instruments/opentelemetry.py
sklearn_instrumentation/instruments/prometheus.py
sklearn_instrumentation/instruments/pyinstrument.py
sklearn_instrumentation/instruments/statsd.py
sklearn_instrumentation/testing.py
sklearn_instrumentation/types.py
sklearn_instrumentation/utils.py
sklearn_instrumentation-0.13.0.dist-info/LICENSE.txt
sklearn_instrumentation-0.13.0.dist-info/WHEEL
sklearn_instrumentation-0.13.0.dist-info/METADATA
sklearn_instrumentation-0.13.0.dist-info/RECORD
