Metadata-Version: 2.1
Name: sklearn-instrumentation
Version: 0.13.0
Summary: scikit-learn instrumentation tooling
Home-page: https://github.com/crflynn/sklearn-instrumentation
License: MIT
Keywords: scikit-learn,instrumentation,machine,learning
Author: flynn
Author-email: crf204@gmail.com
Requires-Python: >=3.7.0
Classifier: Development Status :: 3 - Alpha
Classifier: Intended Audience :: Science/Research
Classifier: License :: OSI Approved :: MIT License
Classifier: Natural Language :: English
Classifier: Programming Language :: Python :: 3
Classifier: Programming Language :: Python :: 3.10
Classifier: Programming Language :: Python :: 3.7
Classifier: Programming Language :: Python :: 3.8
Classifier: Programming Language :: Python :: 3.9
Classifier: Programming Language :: Python :: Implementation :: CPython
Classifier: Topic :: Scientific/Engineering
Provides-Extra: all
Provides-Extra: datadog
Provides-Extra: memory-profiler
Provides-Extra: opentelemetry
Provides-Extra: prometheus
Provides-Extra: pyinstrument
Provides-Extra: statsd
Requires-Dist: ddtrace (>=0.48.0); extra == "all" or extra == "datadog"
Requires-Dist: memory-profiler (>=0.58.0); extra == "all" or extra == "memory-profiler"
Requires-Dist: opentelemetry-api (>=1.0.0); extra == "all" or extra == "opentelemetry"
Requires-Dist: prometheus-client (>=0.10.1); extra == "all" or extra == "prometheus"
Requires-Dist: pyinstrument (>=3.4.1); extra == "all" or extra == "pyinstrument"
Requires-Dist: scikit-learn
Requires-Dist: statsd (>=3.3.0); extra == "all" or extra == "statsd"
Project-URL: Documentation, https://sklearn-instrumentation.readthedocs.io/en/latest/
Project-URL: Repository, https://github.com/crflynn/sklearn-instrumentation
